dcm_schememo/__init__.py
dcm_schememo/vcs_parser.py
dcm_schememo-1.0.1.dist-info/LICENSE
dcm_schememo-1.0.1.dist-info/METADATA
dcm_schememo-1.0.1.dist-info/WHEEL
dcm_schememo-1.0.1.dist-info/top_level.txt
dcm_schememo-1.0.1.dist-info/RECORD
