Metadata-Version: 2.1
Name: dcm-schememo
Version: 1.0.1
Summary: A Python library for docomo Schedule & Memo App backup data.
Home-page: https://github.com/oboenikui/dcm-schememo
Author: oboenikui
Author-email: oboenikuitwitter@gmail.com
License: UNKNOWN
Platform: UNKNOWN
Classifier: Programming Language :: Python :: 3
Classifier: License :: OSI Approved :: MIT License
Classifier: Operating System :: OS Independent
Requires-Python: >=3.9
License-File: LICENSE
Requires-Dist: icalendar>=5.0.7
